aprsd_gps_extension/__init__.py
aprsd_gps_extension/extension.py
aprsd_gps_extension/gps_processor.py
aprsd_gps_extension/stats.py
aprsd_gps_extension/utils.py
aprsd_gps_extension/cmds/__init__.py
aprsd_gps_extension/cmds/show.py
aprsd_gps_extension/conf/__init__.py
aprsd_gps_extension/conf/main.py
aprsd_gps_extension/conf/opts.py
aprsd_gps_extension/threads/GPSBeaconThread.py
aprsd_gps_extension/threads/__init__.py
aprsd_gps_extension-1.0.0.dist-info/licenses/AUTHORS.rst
aprsd_gps_extension-1.0.0.dist-info/licenses/LICENSE
aprsd_gps_extension-1.0.0.dist-info/METADATA
aprsd_gps_extension-1.0.0.dist-info/WHEEL
aprsd_gps_extension-1.0.0.dist-info/entry_points.txt
aprsd_gps_extension-1.0.0.dist-info/top_level.txt
aprsd_gps_extension-1.0.0.dist-info/RECORD
