Metadata-Version: 2.4
Name: aprsd-gps-extension
Version: 1.0.0
Summary: APRSD GPSD Extension to provide active GPS
Author-email: "Walter A. Boring IV" <waboring@hemna.com>
Maintainer-email: "Walter A. Boring IV" <waboring@hemna.com>
License: 
Project-URL: Homepage, https://github.com/hemna/aprsd-admin-extension
Project-URL: Bug Reports, https://github.com/hemna/aprsd-admin-extension/issues
Project-URL: Source, https://github.com/hemna/aprsd-admin-extension
Project-URL: Documentation, https://aprsd-gps-extension.readthedocs.io/en/latest/
Keywords: aprs,aprs-is,aprsd,aprsd-server,aprsd-client,aprsd-socket,aprsd-socket-server,aprsd-socket-client
Classifier: Development Status :: 5 - Production/Stable
Classifier: Environment :: Console
Classifier: Intended Audience :: Developers
Classifier: Intended Audience :: End Users/Desktop
Classifier: Intended Audience :: Information Technology
Classifier: Topic :: Communications :: Ham Radio
Classifier: Topic :: Internet
Classifier: Programming Language :: Python :: 3 :: Only
Classifier: Programming Language :: Python :: 3
Classifier: Programming Language :: Python :: 3.8
Classifier: Programming Language :: Python :: 3.9
Classifier: Programming Language :: Python :: 3.10
Classifier: Programming Language :: Python :: 3.11
Requires-Python: >=3.10
License-File: LICENSE
License-File: AUTHORS.rst
Requires-Dist: gpsdclient>=1.3.2
Dynamic: license-file
